ollama_service/__init__.py
ollama_service/ollama_service.py
ollama_service_deepsec-1.0.0.dist-info/LICENSE
ollama_service_deepsec-1.0.0.dist-info/METADATA
ollama_service_deepsec-1.0.0.dist-info/WHEEL
ollama_service_deepsec-1.0.0.dist-info/top_level.txt
ollama_service_deepsec-1.0.0.dist-info/RECORD
